splunk_contentctl/Res.yml
splunk_contentctl/__init__.py
splunk_contentctl/actions/deploy.py
splunk_contentctl/actions/detection_testing/README.md
splunk_contentctl/actions/detection_testing/authorize.conf.tar
splunk_contentctl/actions/detection_testing/datamodels.conf.tar
splunk_contentctl/actions/detection_testing/detection_testing_execution.py
splunk_contentctl/actions/detection_testing/generate_detection_coverage_badge.py
splunk_contentctl/actions/detection_testing/indexes.conf.tar
splunk_contentctl/actions/detection_testing/modules/DataManipulation.py
splunk_contentctl/actions/detection_testing/modules/github_service.py
splunk_contentctl/actions/detection_testing/modules/instance_manager.py
splunk_contentctl/actions/detection_testing/modules/shared_test_objects.py
splunk_contentctl/actions/detection_testing/modules/splunk_instance.py
splunk_contentctl/actions/detection_testing/summarize_json.py
splunk_contentctl/actions/doc_gen.py
splunk_contentctl/actions/generate.py
splunk_contentctl/actions/initialize.py
splunk_contentctl/actions/initialize_old.py
splunk_contentctl/actions/new_content.py
splunk_contentctl/actions/reporting.py
splunk_contentctl/actions/test.py
splunk_contentctl/actions/validate.py
splunk_contentctl/contentctl.py
splunk_contentctl/enrichments/attack_enrichment.py
splunk_contentctl/enrichments/cve_enrichment.py
splunk_contentctl/enrichments/splunk_app_enrichment.py
splunk_contentctl/helper/config_handler.py
splunk_contentctl/helper/link_validator.py
splunk_contentctl/helper/logger.py
splunk_contentctl/helper/utils.py
splunk_contentctl/input/baseline_builder.py
splunk_contentctl/input/basic_builder.py
splunk_contentctl/input/detection_builder.py
splunk_contentctl/input/director.py
splunk_contentctl/input/investigation_builder.py
splunk_contentctl/input/new_content_generator.py
splunk_contentctl/input/new_content_questions.py
splunk_contentctl/input/playbook_builder.py
splunk_contentctl/input/story_builder.py
splunk_contentctl/input/yml_reader.py
splunk_contentctl-1.0.7.dist-info/entry_points.txt
splunk_contentctl-1.0.7.dist-info/WHEEL
splunk_contentctl-1.0.7.dist-info/METADATA
splunk_contentctl-1.0.7.dist-info/RECORD
