Metadata-Version: 2.1
Name: splunk-contentctl
Version: 1.0.7
Summary: Splunk Content Control Tool
License: Apache 2.0
Author: STRT
Author-email: research@splunk.com
Requires-Python: >=3.9,<4.0
Classifier: License :: Other/Proprietary License
Classifier: Programming Language :: Python :: 3
Classifier: Programming Language :: Python :: 3.10
Classifier: Programming Language :: Python :: 3.9
Requires-Dist: Jinja2 (>=3.1.2,<4.0.0)
Requires-Dist: PyYAML (>=6.0,<7.0)
Requires-Dist: attackcti (>=0.3.7,<0.4.0)
Requires-Dist: docker (>=6.0.1,<7.0.0)
Requires-Dist: gitpython (>=3.1.29,<4.0.0)
Requires-Dist: psutil (>=5.9.4,<6.0.0)
Requires-Dist: pycvesearch (>=1.2,<2.0)
Requires-Dist: pydantic (>=1.10.2,<2.0.0)
Requires-Dist: questionary (>=1.10.0,<2.0.0)
Requires-Dist: requests (>=2.28.1,<3.0.0)
Requires-Dist: semantic-version (>=2.10.0,<3.0.0)
Requires-Dist: splunk-sdk (>=1.7.2,<2.0.0)
Requires-Dist: validators (>=0.20.0,<0.21.0)
Requires-Dist: xmltodict (>=0.13.0,<0.14.0)
